{
  "TypeScript": 375,
  "Python": 315,
  "Go": 293,
  "Rust": 277,
  "JavaScript": 200,
  "PHP": 127,
  "C++": 117,
  "C#": 116,
  "Java": 96,
  "C": 65,
  "Shell": 59,
  "HTML": 51,
  "CSS": 49,
  "Dart": 43,
  "Kotlin": 37,
  "Lua": 33,
  "Ruby": 29,
  "SCSS": 27,
  "Jupyter Notebook": 15,
  "MDX": 13,
  "Swift": 13,
  "Dockerfile": 13,
  "Vue": 12,
  "Jinja": 10,
  "Smarty": 10,
  "Markdown": 9,
  "PowerShell": 9,
  "Vim Script": 7,
  "Nix": 7,
  "HCL": 7,
  "Zig": 7,
  "Makefile": 6,
  "Scala": 4,
  "Adblock Filter List": 4,
  "XML": 3,
  "Perl": 3,
  "Starlark": 3,
  "Move": 3,
  "Mustache": 3,
  "Crystal": 3,
  "Objective-C": 3,
  "R": 3,
  "Nushell": 2,
  "Rich Text Format": 2,
  "Clojure": 2,
  "Pascal": 2,
  "PLSQL": 2,
  "WebAssembly": 2,
  "Cairo": 2,
  "Emacs Lisp": 2,
  "Bicep": 1,
  "ActionScript": 1,
  "Lean": 1,
  "Jsonnet": 1,
  "Erlang": 1,
  "Nim": 1,
  "Groovy": 1,
  "DM": 1,
  "reStructuredText": 1,
  "GDScript": 1,
  "TeX": 1,
  "Tcl": 1,
  "Svelte": 1,
  "OCaml": 1,
  "CMake": 1,
  "Scheme": 1,
  "ASL": 1,
  "Batchfile": 1,
  "Liquid": 1,
  "F#": 1,
  "Macaulay2": 1,
  "Haskell": 1,
  "Solidity": 1,
  "Visual Basic .NET": 1,
  "Gherkin": 1,
  "Prolog": 1,
  "SystemVerilog": 1
}